[
    {
        "timestamp": "2025-11-05T19:22:09.700642+00:00Z",
        "changes": [
            {
                "team": "CroutonDigital",
                "service": "masp",
                "field": "latest_block_height",
                "full_path": "namada.operator.CroutonDigital.service.masp.latest_block_height",
                "type": "modified",
                "old_value": "4180756",
                "new_value": "4181976"
            },
            {
                "team": "CroutonDigital",
                "service": "masp",
                "field": "sync_state",
                "full_path": "namada.operator.CroutonDigital.service.masp.sync_state",
                "type": "modified",
                "old_value": "sync_nok",
                "new_value": "sync_lag"
            }
        ]
    },
    {
        "timestamp": "2025-11-05T19:33:43.983061+00:00Z",
        "changes": [
            {
                "team": "CroutonDigital",
                "service": "masp",
                "field": "sync_state",
                "full_path": "namada.operator.CroutonDigital.service.masp.sync_state",
                "type": "modified",
                "old_value": "sync_nok",
                "new_value": "sync_lag"
            }
        ]
    },
    {
        "timestamp": "2025-11-05T20:30:34.537322+00:00Z",
        "changes": [
            {
                "team": "CroutonDigital",
                "service": "masp",
                "field": "sync_state",
                "full_path": "namada.operator.CroutonDigital.service.masp.sync_state",
                "type": "modified",
                "old_value": "sync_lag",
                "new_value": "sync_nok"
            },
            {
                "team": "CroutonDigital",
                "service": "masp",
                "field": "latest_block_height",
                "full_path": "namada.operator.CroutonDigital.service.masp.latest_block_height",
                "type": "modified",
                "old_value": "4181976",
                "new_value": "4182168"
            }
        ]
    }
]