[
    {
        "timestamp": "2025-11-06T09:13:38.995610+00:00Z",
        "changes": [
            {
                "team": "Heliax",
                "service": "masp",
                "field": "sync_state",
                "full_path": "namada.operator.Heliax.service.masp.sync_state",
                "type": "modified",
                "old_value": "sync_lag",
                "new_value": "sync_nok"
            },
            {
                "team": "Heliax",
                "service": "rpc",
                "field": "version",
                "full_path": "namada.operator.Heliax.service.rpc.version",
                "type": "modified",
                "old_value": "0.37.16",
                "new_value": "0.37.15"
            },
            {
                "team": "Heliax",
                "service": "rpc",
                "field": "is_up_to_date",
                "full_path": "namada.operator.Heliax.service.rpc.is_up_to_date",
                "type": "modified",
                "old_value": false,
                "new_value": true
            }
        ]
    },
    {
        "timestamp": "2025-11-06T09:29:16.230142+00:00Z",
        "changes": [
            {
                "team": "Heliax",
                "service": "masp",
                "field": "sync_state",
                "full_path": "namada.operator.Heliax.service.masp.sync_state",
                "type": "modified",
                "old_value": "sync_lag",
                "new_value": "sync_ok"
            },
            {
                "team": "Heliax",
                "service": "masp",
                "field": "latest_block_height",
                "full_path": "namada.operator.Heliax.service.masp.latest_block_height",
                "type": "modified",
                "old_value": "4188658",
                "new_value": "4189179"
            }
        ]
    },
    {
        "timestamp": "2025-11-06T09:40:49.967664+00:00Z",
        "changes": [
            {
                "team": "Heliax",
                "service": "masp",
                "field": "sync_state",
                "full_path": "namada.operator.Heliax.service.masp.sync_state",
                "type": "modified",
                "old_value": "sync_nok",
                "new_value": "sync_ok"
            },
            {
                "team": "Heliax",
                "service": "rpc",
                "field": "version",
                "full_path": "namada.operator.Heliax.service.rpc.version",
                "type": "modified",
                "old_value": "0.37.15",
                "new_value": "0.37.16"
            },
            {
                "team": "Heliax",
                "service": "rpc",
                "field": "is_up_to_date",
                "full_path": "namada.operator.Heliax.service.rpc.is_up_to_date",
                "type": "modified",
                "old_value": true,
                "new_value": false
            }
        ]
    },
    {
        "timestamp": "2025-11-06T10:14:27.314087+00:00Z",
        "changes": [
            {
                "team": "Heliax",
                "service": "masp",
                "field": "sync_state",
                "full_path": "namada.operator.Heliax.service.masp.sync_state",
                "type": "modified",
                "old_value": "sync_ok",
                "new_value": "sync_lag"
            }
        ]
    },
    {
        "timestamp": "2025-11-06T10:43:17.726925+00:00Z",
        "changes": [
            {
                "team": "Heliax",
                "service": "masp",
                "field": "sync_state",
                "full_path": "namada.operator.Heliax.service.masp.sync_state",
                "type": "modified",
                "old_value": "sync_lag",
                "new_value": "sync_ok"
            }
        ]
    },
    {
        "timestamp": "2025-11-06T11:10:35.269600+00:00Z",
        "changes": [
            {
                "team": "Heliax",
                "service": "rpc",
                "field": "version",
                "full_path": "namada.operator.Heliax.service.rpc.version",
                "type": "modified",
                "old_value": "0.37.16",
                "new_value": "0.37.15"
            },
            {
                "team": "Heliax",
                "service": "rpc",
                "field": "is_up_to_date",
                "full_path": "namada.operator.Heliax.service.rpc.is_up_to_date",
                "type": "modified",
                "old_value": false,
                "new_value": true
            }
        ]
    },
    {
        "timestamp": "2025-11-06T11:23:21.503297+00:00Z",
        "changes": [
            {
                "team": "Heliax",
                "service": "masp",
                "field": "sync_state",
                "full_path": "namada.operator.Heliax.service.masp.sync_state",
                "type": "modified",
                "old_value": "sync_ok",
                "new_value": "sync_lag"
            },
            {
                "team": "Heliax",
                "service": "masp",
                "field": "latest_block_height",
                "full_path": "namada.operator.Heliax.service.masp.latest_block_height",
                "type": "modified",
                "old_value": "4189687",
                "new_value": "4190136"
            },
            {
                "team": "Heliax",
                "service": "rpc",
                "field": "version",
                "full_path": "namada.operator.Heliax.service.rpc.version",
                "type": "modified",
                "old_value": "0.37.16",
                "new_value": "0.37.15"
            },
            {
                "team": "Heliax",
                "service": "rpc",
                "field": "is_up_to_date",
                "full_path": "namada.operator.Heliax.service.rpc.is_up_to_date",
                "type": "modified",
                "old_value": false,
                "new_value": true
            }
        ]
    },
    {
        "timestamp": "2025-11-06T11:35:36.731012+00:00Z",
        "changes": [
            {
                "team": "Heliax",
                "service": "masp",
                "field": "sync_state",
                "full_path": "namada.operator.Heliax.service.masp.sync_state",
                "type": "modified",
                "old_value": "sync_ok",
                "new_value": "sync_lag"
            }
        ]
    }
]