[
    {
        "timestamp": "2026-01-27T22:14:25.012327+00:00Z",
        "changes": [
            {
                "team": "OriginStake",
                "service": "masp",
                "field": "sync_state",
                "full_path": "namada.operator.OriginStake.service.masp.sync_state",
                "type": "modified",
                "old_value": "sync_ok",
                "new_value": "sync_nok"
            }
        ]
    },
    {
        "timestamp": "2026-01-27T22:29:53.737444+00:00Z",
        "changes": [
            {
                "team": "OriginStake",
                "service": "masp",
                "field": "sync_state",
                "full_path": "namada.operator.OriginStake.service.masp.sync_state",
                "type": "modified",
                "old_value": "sync_ok",
                "new_value": "sync_nok"
            }
        ]
    },
    {
        "timestamp": "2026-01-28T14:01:41.349549+00:00Z",
        "changes": [
            {
                "team": "OriginStake",
                "service": "masp",
                "field": "sync_state",
                "full_path": "namada.operator.OriginStake.service.masp.sync_state",
                "type": "modified",
                "old_value": "sync_nok",
                "new_value": "sync_ok"
            }
        ]
    },
    {
        "timestamp": "2026-01-28T14:02:55.973790+00:00Z",
        "changes": [
            {
                "team": "OriginStake",
                "service": "masp",
                "field": "latest_block_height",
                "full_path": "namada.operator.OriginStake.service.masp.latest_block_height",
                "type": "modified",
                "old_value": "5211741",
                "new_value": "5213587"
            },
            {
                "team": "OriginStake",
                "service": "masp",
                "field": "sync_state",
                "full_path": "namada.operator.OriginStake.service.masp.sync_state",
                "type": "modified",
                "old_value": "sync_nok",
                "new_value": "sync_ok"
            }
        ]
    },
    {
        "timestamp": "2026-01-28T14:54:53.567852+00:00Z",
        "changes": [
            {
                "team": "OriginStake",
                "service": "masp",
                "field": "sync_state",
                "full_path": "namada.operator.OriginStake.service.masp.sync_state",
                "type": "modified",
                "old_value": "sync_ok",
                "new_value": "sync_nok"
            }
        ]
    },
    {
        "timestamp": "2026-01-28T14:58:43.902699+00:00Z",
        "changes": [
            {
                "team": "OriginStake",
                "service": "masp",
                "field": "sync_state",
                "full_path": "namada.operator.OriginStake.service.masp.sync_state",
                "type": "modified",
                "old_value": "sync_ok",
                "new_value": "sync_nok"
            }
        ]
    },
    {
        "timestamp": "2026-01-28T16:27:02.294107+00:00Z",
        "changes": [
            {
                "team": "OriginStake",
                "service": "interface",
                "field": "status",
                "full_path": "namada.operator.OriginStake.interface.status",
                "type": "modified",
                "old_value": "up",
                "new_value": "down"
            },
            {
                "team": "OriginStake",
                "service": "interface",
                "field": "version",
                "full_path": "namada.operator.OriginStake.interface.version",
                "type": "modified",
                "old_value": "1.31.4",
                "new_value": "n/a"
            }
        ]
    },
    {
        "timestamp": "2026-01-28T16:49:37.305087+00:00Z",
        "changes": [
            {
                "team": "OriginStake",
                "service": "interface",
                "field": "version",
                "full_path": "namada.operator.OriginStake.interface.version",
                "type": "modified",
                "old_value": "1.31.4",
                "new_value": "n/a"
            },
            {
                "team": "OriginStake",
                "service": "interface",
                "field": "status",
                "full_path": "namada.operator.OriginStake.interface.status",
                "type": "modified",
                "old_value": "up",
                "new_value": "down"
            }
        ]
    },
    {
        "timestamp": "2026-01-28T17:04:42.915717+00:00Z",
        "changes": [
            {
                "team": "OriginStake",
                "service": "interface",
                "field": "status",
                "full_path": "namada.operator.OriginStake.interface.status",
                "type": "modified",
                "old_value": "down",
                "new_value": "up"
            },
            {
                "team": "OriginStake",
                "service": "interface",
                "field": "version",
                "full_path": "namada.operator.OriginStake.interface.version",
                "type": "modified",
                "old_value": "n/a",
                "new_value": "1.31.4"
            }
        ]
    },
    {
        "timestamp": "2026-01-28T17:39:16.854420+00:00Z",
        "changes": [
            {
                "team": "OriginStake",
                "service": "interface",
                "field": "version",
                "full_path": "namada.operator.OriginStake.interface.version",
                "type": "modified",
                "old_value": "n/a",
                "new_value": "1.31.4"
            },
            {
                "team": "OriginStake",
                "service": "interface",
                "field": "status",
                "full_path": "namada.operator.OriginStake.interface.status",
                "type": "modified",
                "old_value": "down",
                "new_value": "up"
            }
        ]
    },
    {
        "timestamp": "2026-01-28T20:19:22.565103+00:00Z",
        "changes": [
            {
                "team": "OriginStake",
                "service": "masp",
                "field": "sync_state",
                "full_path": "namada.operator.OriginStake.service.masp.sync_state",
                "type": "modified",
                "old_value": "sync_nok",
                "new_value": "sync_ok"
            }
        ]
    }
]