[
    {
        "timestamp": "2025-11-11T16:14:38.902843+00:00Z",
        "changes": [
            {
                "team": "Palamar",
                "service": "masp",
                "field": "sync_state",
                "full_path": "namada.operator.Palamar.service.masp.sync_state",
                "type": "modified",
                "old_value": "sync_ok",
                "new_value": "sync_nok"
            }
        ]
    },
    {
        "timestamp": "2025-11-11T16:34:24.508026+00:00Z",
        "changes": [
            {
                "team": "Palamar",
                "service": "masp",
                "field": "sync_state",
                "full_path": "namada.operator.Palamar.service.masp.sync_state",
                "type": "modified",
                "old_value": "sync_ok",
                "new_value": "sync_nok"
            },
            {
                "team": "Palamar",
                "service": "masp",
                "field": "latest_block_height",
                "full_path": "namada.operator.Palamar.service.masp.latest_block_height",
                "type": "modified",
                "old_value": "4254060",
                "new_value": "4254131"
            }
        ]
    },
    {
        "timestamp": "2025-11-11T17:11:07.408959+00:00Z",
        "changes": [
            {
                "team": "Palamar",
                "service": "masp",
                "field": "sync_state",
                "full_path": "namada.operator.Palamar.service.masp.sync_state",
                "type": "modified",
                "old_value": "sync_nok",
                "new_value": "sync_lag"
            }
        ]
    },
    {
        "timestamp": "2025-11-11T17:39:16.751313+00:00Z",
        "changes": [
            {
                "team": "Palamar",
                "service": "masp",
                "field": "sync_state",
                "full_path": "namada.operator.Palamar.service.masp.sync_state",
                "type": "modified",
                "old_value": "sync_lag",
                "new_value": "sync_nok"
            }
        ]
    },
    {
        "timestamp": "2025-11-11T18:37:06.130518+00:00Z",
        "changes": [
            {
                "team": "Palamar",
                "service": "masp",
                "field": "sync_state",
                "full_path": "namada.operator.Palamar.service.masp.sync_state",
                "type": "modified",
                "old_value": "sync_nok",
                "new_value": "sync_lag"
            },
            {
                "team": "Palamar",
                "service": "masp",
                "field": "latest_block_height",
                "full_path": "namada.operator.Palamar.service.masp.latest_block_height",
                "type": "modified",
                "old_value": "4254900",
                "new_value": "4255632"
            }
        ]
    },
    {
        "timestamp": "2025-11-11T18:47:01.254281+00:00Z",
        "changes": [
            {
                "team": "Palamar",
                "service": "masp",
                "field": "sync_state",
                "full_path": "namada.operator.Palamar.service.masp.sync_state",
                "type": "modified",
                "old_value": "sync_nok",
                "new_value": "sync_lag"
            }
        ]
    },
    {
        "timestamp": "2025-11-11T19:09:02.130491+00:00Z",
        "changes": [
            {
                "team": "Palamar",
                "service": "masp",
                "field": "sync_state",
                "full_path": "namada.operator.Palamar.service.masp.sync_state",
                "type": "modified",
                "old_value": "sync_lag",
                "new_value": "sync_nok"
            }
        ]
    },
    {
        "timestamp": "2025-11-11T19:33:11.478516+00:00Z",
        "changes": [
            {
                "team": "Palamar",
                "service": "masp",
                "field": "sync_state",
                "full_path": "namada.operator.Palamar.service.masp.sync_state",
                "type": "modified",
                "old_value": "sync_nok",
                "new_value": "sync_lag"
            }
        ]
    },
    {
        "timestamp": "2025-11-11T20:13:07.786966+00:00Z",
        "changes": [
            {
                "team": "Palamar",
                "service": "masp",
                "field": "sync_state",
                "full_path": "namada.operator.Palamar.service.masp.sync_state",
                "type": "modified",
                "old_value": "sync_lag",
                "new_value": "sync_nok"
            }
        ]
    },
    {
        "timestamp": "2025-11-11T20:38:52.697999+00:00Z",
        "changes": [
            {
                "team": "Palamar",
                "service": "masp",
                "field": "sync_state",
                "full_path": "namada.operator.Palamar.service.masp.sync_state",
                "type": "modified",
                "old_value": "sync_nok",
                "new_value": "sync_lag"
            }
        ]
    },
    {
        "timestamp": "2025-11-11T21:10:27.429844+00:00Z",
        "changes": [
            {
                "team": "Palamar",
                "service": "masp",
                "field": "sync_state",
                "full_path": "namada.operator.Palamar.service.masp.sync_state",
                "type": "modified",
                "old_value": "sync_lag",
                "new_value": "sync_ok"
            }
        ]
    },
    {
        "timestamp": "2025-11-11T21:23:42.303704+00:00Z",
        "changes": [
            {
                "team": "Palamar",
                "service": "masp",
                "field": "latest_block_height",
                "full_path": "namada.operator.Palamar.service.masp.latest_block_height",
                "type": "modified",
                "old_value": "4256642",
                "new_value": "4256950"
            },
            {
                "team": "Palamar",
                "service": "masp",
                "field": "sync_state",
                "full_path": "namada.operator.Palamar.service.masp.sync_state",
                "type": "modified",
                "old_value": "sync_lag",
                "new_value": "sync_nok"
            }
        ]
    },
    {
        "timestamp": "2025-11-11T21:35:45.353465+00:00Z",
        "changes": [
            {
                "team": "Palamar",
                "service": "masp",
                "field": "sync_state",
                "full_path": "namada.operator.Palamar.service.masp.sync_state",
                "type": "modified",
                "old_value": "sync_ok",
                "new_value": "sync_nok"
            }
        ]
    },
    {
        "timestamp": "2025-11-11T22:11:54.807652+00:00Z",
        "changes": [
            {
                "team": "Palamar",
                "service": "masp",
                "field": "sync_state",
                "full_path": "namada.operator.Palamar.service.masp.sync_state",
                "type": "modified",
                "old_value": "sync_nok",
                "new_value": "sync_lag"
            }
        ]
    },
    {
        "timestamp": "2025-11-11T22:38:58.419292+00:00Z",
        "changes": [
            {
                "team": "Palamar",
                "service": "masp",
                "field": "sync_state",
                "full_path": "namada.operator.Palamar.service.masp.sync_state",
                "type": "modified",
                "old_value": "sync_lag",
                "new_value": "sync_nok"
            }
        ]
    },
    {
        "timestamp": "2025-11-11T23:10:38.652543+00:00Z",
        "changes": [
            {
                "team": "Palamar",
                "service": "masp",
                "field": "sync_state",
                "full_path": "namada.operator.Palamar.service.masp.sync_state",
                "type": "modified",
                "old_value": "sync_nok",
                "new_value": "sync_ok"
            }
        ]
    },
    {
        "timestamp": "2025-11-11T23:35:13.770439+00:00Z",
        "changes": [
            {
                "team": "Palamar",
                "service": "masp",
                "field": "sync_state",
                "full_path": "namada.operator.Palamar.service.masp.sync_state",
                "type": "modified",
                "old_value": "sync_ok",
                "new_value": "sync_nok"
            }
        ]
    },
    {
        "timestamp": "2025-11-12T03:32:44.719698+00:00Z",
        "changes": [
            {
                "team": "Palamar",
                "service": "masp",
                "field": "sync_state",
                "full_path": "namada.operator.Palamar.service.masp.sync_state",
                "type": "modified",
                "old_value": "sync_nok",
                "new_value": "sync_lag"
            }
        ]
    },
    {
        "timestamp": "2025-11-12T03:33:15.186556+00:00Z",
        "changes": [
            {
                "team": "Palamar",
                "service": "masp",
                "field": "sync_state",
                "full_path": "namada.operator.Palamar.service.masp.sync_state",
                "type": "modified",
                "old_value": "sync_nok",
                "new_value": "sync_lag"
            },
            {
                "team": "Palamar",
                "service": "masp",
                "field": "latest_block_height",
                "full_path": "namada.operator.Palamar.service.masp.latest_block_height",
                "type": "modified",
                "old_value": "4259048",
                "new_value": "4260069"
            }
        ]
    },
    {
        "timestamp": "2025-11-12T04:31:56.371914+00:00Z",
        "changes": [
            {
                "team": "Palamar",
                "service": "masp",
                "field": "sync_state",
                "full_path": "namada.operator.Palamar.service.masp.sync_state",
                "type": "modified",
                "old_value": "sync_lag",
                "new_value": "sync_nok"
            },
            {
                "team": "Palamar",
                "service": "masp",
                "field": "latest_block_height",
                "full_path": "namada.operator.Palamar.service.masp.latest_block_height",
                "type": "modified",
                "old_value": "4260069",
                "new_value": "4260452"
            }
        ]
    },
    {
        "timestamp": "2025-11-12T04:42:56.082682+00:00Z",
        "changes": [
            {
                "team": "Palamar",
                "service": "masp",
                "field": "sync_state",
                "full_path": "namada.operator.Palamar.service.masp.sync_state",
                "type": "modified",
                "old_value": "sync_lag",
                "new_value": "sync_nok"
            }
        ]
    }
]