[
    {
        "timestamp": "2025-11-12T21:11:05.177572+00:00Z",
        "changes": [
            {
                "team": "Palamar",
                "service": "masp",
                "field": "sync_state",
                "full_path": "namada.operator.Palamar.service.masp.sync_state",
                "type": "modified",
                "old_value": "sync_ok",
                "new_value": "sync_lag"
            }
        ]
    },
    {
        "timestamp": "2025-11-12T21:24:52.288116+00:00Z",
        "changes": [
            {
                "team": "Palamar",
                "service": "masp",
                "field": "latest_block_height",
                "full_path": "namada.operator.Palamar.service.masp.latest_block_height",
                "type": "modified",
                "old_value": "4269149",
                "new_value": "4269619"
            },
            {
                "team": "Palamar",
                "service": "masp",
                "field": "sync_state",
                "full_path": "namada.operator.Palamar.service.masp.sync_state",
                "type": "modified",
                "old_value": "sync_ok",
                "new_value": "sync_lag"
            }
        ]
    }
]