[
    {
        "timestamp": "2026-01-02T14:13:03.644224+00:00Z",
        "changes": [
            {
                "team": null,
                "service": null,
                "field": "housefire_reference_latest_block_height",
                "full_path": "housefire_reference_latest_block_height",
                "type": "modified",
                "old_value": "3932220",
                "new_value": "3932364"
            }
        ]
    },
    {
        "timestamp": "2026-01-02T14:42:34.843140+00:00Z",
        "changes": [
            {
                "team": null,
                "service": null,
                "field": "housefire_reference_latest_block_height",
                "full_path": "housefire_reference_latest_block_height",
                "type": "modified",
                "old_value": "3932364",
                "new_value": "3932549"
            }
        ]
    },
    {
        "timestamp": "2026-01-02T14:28:40.114510+00:00Z",
        "changes": [
            {
                "team": null,
                "service": null,
                "field": "housefire_reference_latest_block_height",
                "full_path": "housefire_reference_latest_block_height",
                "type": "modified",
                "old_value": "3932220",
                "new_value": "3932549"
            }
        ]
    },
    {
        "timestamp": "2026-01-02T15:13:06.652138+00:00Z",
        "changes": [
            {
                "team": null,
                "service": null,
                "field": "housefire_reference_latest_block_height",
                "full_path": "housefire_reference_latest_block_height",
                "type": "modified",
                "old_value": "3932549",
                "new_value": "3932740"
            }
        ]
    },
    {
        "timestamp": "2026-01-02T15:29:36.477819+00:00Z",
        "changes": [
            {
                "team": null,
                "service": null,
                "field": "housefire_reference_latest_block_height",
                "full_path": "housefire_reference_latest_block_height",
                "type": "modified",
                "old_value": "3932549",
                "new_value": "3932976"
            }
        ]
    },
    {
        "timestamp": "2026-01-02T15:40:50.318742+00:00Z",
        "changes": [
            {
                "team": null,
                "service": null,
                "field": "housefire_reference_latest_block_height",
                "full_path": "housefire_reference_latest_block_height",
                "type": "modified",
                "old_value": "3932740",
                "new_value": "3932976"
            }
        ]
    },
    {
        "timestamp": "2026-01-02T16:14:46.570998+00:00Z",
        "changes": [
            {
                "team": null,
                "service": null,
                "field": "housefire_reference_latest_block_height",
                "full_path": "housefire_reference_latest_block_height",
                "type": "modified",
                "old_value": "3932976",
                "new_value": "3933145"
            }
        ]
    },
    {
        "timestamp": "2026-01-02T16:34:55.316465+00:00Z",
        "changes": [
            {
                "team": null,
                "service": null,
                "field": "housefire_reference_latest_block_height",
                "full_path": "housefire_reference_latest_block_height",
                "type": "modified",
                "old_value": "3932976",
                "new_value": "3933421"
            }
        ]
    },
    {
        "timestamp": "2026-01-02T16:46:37.192333+00:00Z",
        "changes": [
            {
                "team": null,
                "service": null,
                "field": "housefire_reference_latest_block_height",
                "full_path": "housefire_reference_latest_block_height",
                "type": "modified",
                "old_value": "3933145",
                "new_value": "3933421"
            }
        ]
    },
    {
        "timestamp": "2026-01-02T17:10:55.950840+00:00Z",
        "changes": [
            {
                "team": null,
                "service": null,
                "field": "housefire_reference_latest_block_height",
                "full_path": "housefire_reference_latest_block_height",
                "type": "modified",
                "old_value": "3933421",
                "new_value": "3933612"
            }
        ]
    },
    {
        "timestamp": "2026-01-02T17:25:16.729604+00:00Z",
        "changes": [
            {
                "team": null,
                "service": null,
                "field": "housefire_reference_latest_block_height",
                "full_path": "housefire_reference_latest_block_height",
                "type": "modified",
                "old_value": "3933421",
                "new_value": "3933793"
            }
        ]
    },
    {
        "timestamp": "2026-01-02T17:39:40.755232+00:00Z",
        "changes": [
            {
                "team": null,
                "service": null,
                "field": "housefire_reference_latest_block_height",
                "full_path": "housefire_reference_latest_block_height",
                "type": "modified",
                "old_value": "3933612",
                "new_value": "3933793"
            }
        ]
    }
]