[
    {
        "timestamp": "2025-10-27T05:42:27.634242+00:00Z",
        "changes": [
            {
                "team": null,
                "service": null,
                "field": "housefire_reference_latest_block_height",
                "full_path": "housefire_reference_latest_block_height",
                "type": "modified",
                "old_value": "3252888",
                "new_value": "3253072"
            }
        ]
    },
    {
        "timestamp": "2025-10-27T06:32:07.559287+00:00Z",
        "changes": [
            {
                "team": null,
                "service": null,
                "field": "housefire_reference_latest_block_height",
                "full_path": "housefire_reference_latest_block_height",
                "type": "modified",
                "old_value": "3253072",
                "new_value": "3253543"
            }
        ]
    },
    {
        "timestamp": "2025-10-27T06:27:09.360927+00:00Z",
        "changes": [
            {
                "team": null,
                "service": null,
                "field": "housefire_reference_latest_block_height",
                "full_path": "housefire_reference_latest_block_height",
                "type": "modified",
                "old_value": "3253072",
                "new_value": "3253268"
            }
        ]
    },
    {
        "timestamp": "2025-10-27T06:53:41.112995+00:00Z",
        "changes": [
            {
                "team": null,
                "service": null,
                "field": "housefire_reference_latest_block_height",
                "full_path": "housefire_reference_latest_block_height",
                "type": "modified",
                "old_value": "3253268",
                "new_value": "3253543"
            }
        ]
    },
    {
        "timestamp": "2025-10-27T07:18:53.966782+00:00Z",
        "changes": [
            {
                "team": null,
                "service": null,
                "field": "housefire_reference_latest_block_height",
                "full_path": "housefire_reference_latest_block_height",
                "type": "modified",
                "old_value": "3253543",
                "new_value": "3253777"
            }
        ]
    },
    {
        "timestamp": "2025-10-27T07:16:32.704329+00:00Z",
        "changes": [
            {
                "team": null,
                "service": null,
                "field": "housefire_reference_latest_block_height",
                "full_path": "housefire_reference_latest_block_height",
                "type": "modified",
                "old_value": "3253543",
                "new_value": "3253777"
            }
        ]
    },
    {
        "timestamp": "2025-10-27T07:39:03.987557+00:00Z",
        "changes": [
            {
                "team": null,
                "service": null,
                "field": "housefire_reference_latest_block_height",
                "full_path": "housefire_reference_latest_block_height",
                "type": "modified",
                "old_value": "3253777",
                "new_value": "3253928"
            }
        ]
    },
    {
        "timestamp": "2025-10-27T07:37:58.133145+00:00Z",
        "changes": [
            {
                "team": null,
                "service": null,
                "field": "housefire_reference_latest_block_height",
                "full_path": "housefire_reference_latest_block_height",
                "type": "modified",
                "old_value": "3253777",
                "new_value": "3253928"
            }
        ]
    },
    {
        "timestamp": "2025-10-27T08:27:00.795560+00:00Z",
        "changes": [
            {
                "team": null,
                "service": null,
                "field": "housefire_reference_latest_block_height",
                "full_path": "housefire_reference_latest_block_height",
                "type": "modified",
                "old_value": "3253928",
                "new_value": "3254084"
            }
        ]
    },
    {
        "timestamp": "2025-10-27T08:22:42.824414+00:00Z",
        "changes": [
            {
                "team": null,
                "service": null,
                "field": "housefire_reference_latest_block_height",
                "full_path": "housefire_reference_latest_block_height",
                "type": "modified",
                "old_value": "3253928",
                "new_value": "3254084"
            }
        ]
    },
    {
        "timestamp": "2025-10-27T08:49:35.692178+00:00Z",
        "changes": [
            {
                "team": null,
                "service": null,
                "field": "housefire_reference_latest_block_height",
                "full_path": "housefire_reference_latest_block_height",
                "type": "modified",
                "old_value": "3254084",
                "new_value": "3254372"
            }
        ]
    },
    {
        "timestamp": "2025-10-27T08:47:23.109397+00:00Z",
        "changes": [
            {
                "team": null,
                "service": null,
                "field": "housefire_reference_latest_block_height",
                "full_path": "housefire_reference_latest_block_height",
                "type": "modified",
                "old_value": "3254084",
                "new_value": "3254372"
            }
        ]
    },
    {
        "timestamp": "2025-10-27T09:24:00.804530+00:00Z",
        "changes": [
            {
                "team": null,
                "service": null,
                "field": "housefire_reference_latest_block_height",
                "full_path": "housefire_reference_latest_block_height",
                "type": "modified",
                "old_value": "3254372",
                "new_value": "3254572"
            }
        ]
    },
    {
        "timestamp": "2025-10-27T09:20:19.038761+00:00Z",
        "changes": [
            {
                "team": null,
                "service": null,
                "field": "housefire_reference_latest_block_height",
                "full_path": "housefire_reference_latest_block_height",
                "type": "modified",
                "old_value": "3254372",
                "new_value": "3254572"
            }
        ]
    },
    {
        "timestamp": "2025-10-27T09:44:14.651173+00:00Z",
        "changes": [
            {
                "team": null,
                "service": null,
                "field": "housefire_reference_latest_block_height",
                "full_path": "housefire_reference_latest_block_height",
                "type": "modified",
                "old_value": "3254572",
                "new_value": "3254778"
            }
        ]
    },
    {
        "timestamp": "2025-10-27T09:42:57.213392+00:00Z",
        "changes": [
            {
                "team": null,
                "service": null,
                "field": "housefire_reference_latest_block_height",
                "full_path": "housefire_reference_latest_block_height",
                "type": "modified",
                "old_value": "3254572",
                "new_value": "3254778"
            }
        ]
    },
    {
        "timestamp": "2025-10-27T10:22:52.790146+00:00Z",
        "changes": [
            {
                "team": null,
                "service": null,
                "field": "housefire_reference_latest_block_height",
                "full_path": "housefire_reference_latest_block_height",
                "type": "modified",
                "old_value": "3254778",
                "new_value": "3254962"
            }
        ]
    },
    {
        "timestamp": "2025-10-27T10:45:51.085068+00:00Z",
        "changes": [
            {
                "team": null,
                "service": null,
                "field": "housefire_reference_latest_block_height",
                "full_path": "housefire_reference_latest_block_height",
                "type": "modified",
                "old_value": "3254962",
                "new_value": "3255193"
            }
        ]
    },
    {
        "timestamp": "2025-10-27T10:44:45.603844+00:00Z",
        "changes": [
            {
                "team": null,
                "service": null,
                "field": "housefire_reference_latest_block_height",
                "full_path": "housefire_reference_latest_block_height",
                "type": "modified",
                "old_value": "3254778",
                "new_value": "3255193"
            }
        ]
    },
    {
        "timestamp": "2025-10-27T11:17:06.971085+00:00Z",
        "changes": [
            {
                "team": null,
                "service": null,
                "field": "housefire_reference_latest_block_height",
                "full_path": "housefire_reference_latest_block_height",
                "type": "modified",
                "old_value": "3255193",
                "new_value": "3255392"
            }
        ]
    },
    {
        "timestamp": "2025-10-27T11:14:25.432782+00:00Z",
        "changes": [
            {
                "team": null,
                "service": null,
                "field": "housefire_reference_latest_block_height",
                "full_path": "housefire_reference_latest_block_height",
                "type": "modified",
                "old_value": "3255193",
                "new_value": "3255392"
            }
        ]
    },
    {
        "timestamp": "2025-10-27T11:38:28.180916+00:00Z",
        "changes": [
            {
                "team": null,
                "service": null,
                "field": "housefire_reference_latest_block_height",
                "full_path": "housefire_reference_latest_block_height",
                "type": "modified",
                "old_value": "3255392",
                "new_value": "3255591"
            }
        ]
    },
    {
        "timestamp": "2025-10-27T11:37:17.222556+00:00Z",
        "changes": [
            {
                "team": null,
                "service": null,
                "field": "housefire_reference_latest_block_height",
                "full_path": "housefire_reference_latest_block_height",
                "type": "modified",
                "old_value": "3255392",
                "new_value": "3255591"
            }
        ]
    },
    {
        "timestamp": "2025-10-27T12:41:35.658474+00:00Z",
        "changes": [
            {
                "team": null,
                "service": null,
                "field": "housefire_reference_latest_block_height",
                "full_path": "housefire_reference_latest_block_height",
                "type": "modified",
                "old_value": "3255591",
                "new_value": "3256108"
            }
        ]
    },
    {
        "timestamp": "2025-10-27T12:35:16.066385+00:00Z",
        "changes": [
            {
                "team": null,
                "service": null,
                "field": "housefire_reference_latest_block_height",
                "full_path": "housefire_reference_latest_block_height",
                "type": "modified",
                "old_value": "3255591",
                "new_value": "3256108"
            }
        ]
    },
    {
        "timestamp": "2025-10-27T13:31:21.974313+00:00Z",
        "changes": [
            {
                "team": null,
                "service": null,
                "field": "housefire_reference_latest_block_height",
                "full_path": "housefire_reference_latest_block_height",
                "type": "modified",
                "old_value": "3256108",
                "new_value": "3256397"
            }
        ]
    },
    {
        "timestamp": "2025-10-27T13:28:58.426132+00:00Z",
        "changes": [
            {
                "team": null,
                "service": null,
                "field": "housefire_reference_latest_block_height",
                "full_path": "housefire_reference_latest_block_height",
                "type": "modified",
                "old_value": "3256108",
                "new_value": "3256397"
            }
        ]
    },
    {
        "timestamp": "2025-10-27T14:19:56.137880+00:00Z",
        "changes": [
            {
                "team": null,
                "service": null,
                "field": "housefire_reference_latest_block_height",
                "full_path": "housefire_reference_latest_block_height",
                "type": "modified",
                "old_value": "3256397",
                "new_value": "3256849"
            }
        ]
    },
    {
        "timestamp": "2025-10-27T14:17:09.392677+00:00Z",
        "changes": [
            {
                "team": null,
                "service": null,
                "field": "housefire_reference_latest_block_height",
                "full_path": "housefire_reference_latest_block_height",
                "type": "modified",
                "old_value": "3256397",
                "new_value": "3256690"
            }
        ]
    },
    {
        "timestamp": "2025-10-27T14:40:53.460769+00:00Z",
        "changes": [
            {
                "team": null,
                "service": null,
                "field": "housefire_reference_latest_block_height",
                "full_path": "housefire_reference_latest_block_height",
                "type": "modified",
                "old_value": "3256690",
                "new_value": "3256849"
            }
        ]
    },
    {
        "timestamp": "2025-10-27T15:20:48.003543+00:00Z",
        "changes": [
            {
                "team": null,
                "service": null,
                "field": "housefire_reference_latest_block_height",
                "full_path": "housefire_reference_latest_block_height",
                "type": "modified",
                "old_value": "3256849",
                "new_value": "3257054"
            }
        ]
    },
    {
        "timestamp": "2025-10-27T15:17:34.936332+00:00Z",
        "changes": [
            {
                "team": null,
                "service": null,
                "field": "housefire_reference_latest_block_height",
                "full_path": "housefire_reference_latest_block_height",
                "type": "modified",
                "old_value": "3256849",
                "new_value": "3257054"
            }
        ]
    },
    {
        "timestamp": "2025-10-27T15:40:04.806998+00:00Z",
        "changes": [
            {
                "team": null,
                "service": null,
                "field": "housefire_reference_latest_block_height",
                "full_path": "housefire_reference_latest_block_height",
                "type": "modified",
                "old_value": "3257054",
                "new_value": "3257280"
            }
        ]
    },
    {
        "timestamp": "2025-10-27T15:38:35.820018+00:00Z",
        "changes": [
            {
                "team": null,
                "service": null,
                "field": "housefire_reference_latest_block_height",
                "full_path": "housefire_reference_latest_block_height",
                "type": "modified",
                "old_value": "3257054",
                "new_value": "3257280"
            }
        ]
    },
    {
        "timestamp": "2025-10-27T16:25:32.319549+00:00Z",
        "changes": [
            {
                "team": null,
                "service": null,
                "field": "housefire_reference_latest_block_height",
                "full_path": "housefire_reference_latest_block_height",
                "type": "modified",
                "old_value": "3257280",
                "new_value": "3257717"
            }
        ]
    },
    {
        "timestamp": "2025-10-27T16:21:09.208598+00:00Z",
        "changes": [
            {
                "team": null,
                "service": null,
                "field": "housefire_reference_latest_block_height",
                "full_path": "housefire_reference_latest_block_height",
                "type": "modified",
                "old_value": "3257280",
                "new_value": "3257451"
            }
        ]
    },
    {
        "timestamp": "2025-10-27T16:47:30.578535+00:00Z",
        "changes": [
            {
                "team": null,
                "service": null,
                "field": "housefire_reference_latest_block_height",
                "full_path": "housefire_reference_latest_block_height",
                "type": "modified",
                "old_value": "3257451",
                "new_value": "3257717"
            }
        ]
    },
    {
        "timestamp": "2025-10-27T17:16:39.202888+00:00Z",
        "changes": [
            {
                "team": null,
                "service": null,
                "field": "housefire_reference_latest_block_height",
                "full_path": "housefire_reference_latest_block_height",
                "type": "modified",
                "old_value": "3257717",
                "new_value": "3257923"
            }
        ]
    },
    {
        "timestamp": "2025-10-27T17:14:03.279980+00:00Z",
        "changes": [
            {
                "team": null,
                "service": null,
                "field": "housefire_reference_latest_block_height",
                "full_path": "housefire_reference_latest_block_height",
                "type": "modified",
                "old_value": "3257717",
                "new_value": "3257923"
            }
        ]
    },
    {
        "timestamp": "2025-10-27T17:39:49.305832+00:00Z",
        "changes": [
            {
                "team": null,
                "service": null,
                "field": "housefire_reference_latest_block_height",
                "full_path": "housefire_reference_latest_block_height",
                "type": "modified",
                "old_value": "3257923",
                "new_value": "3258099"
            }
        ]
    },
    {
        "timestamp": "2025-10-27T17:38:40.275658+00:00Z",
        "changes": [
            {
                "team": null,
                "service": null,
                "field": "housefire_reference_latest_block_height",
                "full_path": "housefire_reference_latest_block_height",
                "type": "modified",
                "old_value": "3257923",
                "new_value": "3258099"
            }
        ]
    },
    {
        "timestamp": "2025-10-27T18:28:34.007740+00:00Z",
        "changes": [
            {
                "team": null,
                "service": null,
                "field": "housefire_reference_latest_block_height",
                "full_path": "housefire_reference_latest_block_height",
                "type": "modified",
                "old_value": "3258099",
                "new_value": "3258573"
            }
        ]
    },
    {
        "timestamp": "2025-10-27T18:23:49.411749+00:00Z",
        "changes": [
            {
                "team": null,
                "service": null,
                "field": "housefire_reference_latest_block_height",
                "full_path": "housefire_reference_latest_block_height",
                "type": "modified",
                "old_value": "3258099",
                "new_value": "3258283"
            }
        ]
    },
    {
        "timestamp": "2025-10-27T18:48:08.467458+00:00Z",
        "changes": [
            {
                "team": null,
                "service": null,
                "field": "housefire_reference_latest_block_height",
                "full_path": "housefire_reference_latest_block_height",
                "type": "modified",
                "old_value": "3258283",
                "new_value": "3258573"
            }
        ]
    },
    {
        "timestamp": "2025-10-27T19:15:03.006546+00:00Z",
        "changes": [
            {
                "team": null,
                "service": null,
                "field": "housefire_reference_latest_block_height",
                "full_path": "housefire_reference_latest_block_height",
                "type": "modified",
                "old_value": "3258573",
                "new_value": "3258770"
            }
        ]
    },
    {
        "timestamp": "2025-10-27T19:12:29.073533+00:00Z",
        "changes": [
            {
                "team": null,
                "service": null,
                "field": "housefire_reference_latest_block_height",
                "full_path": "housefire_reference_latest_block_height",
                "type": "modified",
                "old_value": "3258573",
                "new_value": "3258770"
            }
        ]
    },
    {
        "timestamp": "2025-10-27T19:37:02.322884+00:00Z",
        "changes": [
            {
                "team": null,
                "service": null,
                "field": "housefire_reference_latest_block_height",
                "full_path": "housefire_reference_latest_block_height",
                "type": "modified",
                "old_value": "3258770",
                "new_value": "3258936"
            }
        ]
    },
    {
        "timestamp": "2025-10-27T19:35:54.052806+00:00Z",
        "changes": [
            {
                "team": null,
                "service": null,
                "field": "housefire_reference_latest_block_height",
                "full_path": "housefire_reference_latest_block_height",
                "type": "modified",
                "old_value": "3258770",
                "new_value": "3258936"
            }
        ]
    },
    {
        "timestamp": "2025-10-27T20:18:55.624334+00:00Z",
        "changes": [
            {
                "team": null,
                "service": null,
                "field": "housefire_reference_latest_block_height",
                "full_path": "housefire_reference_latest_block_height",
                "type": "modified",
                "old_value": "3258936",
                "new_value": "3259361"
            }
        ]
    },
    {
        "timestamp": "2025-10-27T20:16:05.203266+00:00Z",
        "changes": [
            {
                "team": null,
                "service": null,
                "field": "housefire_reference_latest_block_height",
                "full_path": "housefire_reference_latest_block_height",
                "type": "modified",
                "old_value": "3258936",
                "new_value": "3259100"
            }
        ]
    },
    {
        "timestamp": "2025-10-27T20:39:02.512346+00:00Z",
        "changes": [
            {
                "team": null,
                "service": null,
                "field": "housefire_reference_latest_block_height",
                "full_path": "housefire_reference_latest_block_height",
                "type": "modified",
                "old_value": "3259100",
                "new_value": "3259361"
            }
        ]
    },
    {
        "timestamp": "2025-10-27T21:16:31.773209+00:00Z",
        "changes": [
            {
                "team": null,
                "service": null,
                "field": "housefire_reference_latest_block_height",
                "full_path": "housefire_reference_latest_block_height",
                "type": "modified",
                "old_value": "3259361",
                "new_value": "3259550"
            }
        ]
    },
    {
        "timestamp": "2025-10-27T21:14:02.613615+00:00Z",
        "changes": [
            {
                "team": null,
                "service": null,
                "field": "housefire_reference_latest_block_height",
                "full_path": "housefire_reference_latest_block_height",
                "type": "modified",
                "old_value": "3259361",
                "new_value": "3259550"
            }
        ]
    }
]