[
    {
        "timestamp": "2026-01-14T09:20:40.831987+00:00Z",
        "changes": [
            {
                "team": null,
                "service": null,
                "field": "housefire_reference_latest_block_height",
                "full_path": "housefire_reference_latest_block_height",
                "type": "modified",
                "old_value": "4050821",
                "new_value": "4051030"
            }
        ]
    },
    {
        "timestamp": "2026-01-14T09:36:57.309326+00:00Z",
        "changes": [
            {
                "team": null,
                "service": null,
                "field": "housefire_reference_latest_block_height",
                "full_path": "housefire_reference_latest_block_height",
                "type": "modified",
                "old_value": "4050821",
                "new_value": "4051250"
            }
        ]
    },
    {
        "timestamp": "2026-01-14T09:48:54.891497+00:00Z",
        "changes": [
            {
                "team": null,
                "service": null,
                "field": "housefire_reference_latest_block_height",
                "full_path": "housefire_reference_latest_block_height",
                "type": "modified",
                "old_value": "4051030",
                "new_value": "4051250"
            }
        ]
    },
    {
        "timestamp": "2026-01-14T10:15:41.413835+00:00Z",
        "changes": [
            {
                "team": null,
                "service": null,
                "field": "housefire_reference_latest_block_height",
                "full_path": "housefire_reference_latest_block_height",
                "type": "modified",
                "old_value": "4051250",
                "new_value": "4051425"
            }
        ]
    },
    {
        "timestamp": "2026-01-14T10:34:12.376697+00:00Z",
        "changes": [
            {
                "team": null,
                "service": null,
                "field": "housefire_reference_latest_block_height",
                "full_path": "housefire_reference_latest_block_height",
                "type": "modified",
                "old_value": "4051250",
                "new_value": "4051633"
            }
        ]
    },
    {
        "timestamp": "2026-01-14T10:48:28.349083+00:00Z",
        "changes": [
            {
                "team": null,
                "service": null,
                "field": "housefire_reference_latest_block_height",
                "full_path": "housefire_reference_latest_block_height",
                "type": "modified",
                "old_value": "4051425",
                "new_value": "4051633"
            }
        ]
    },
    {
        "timestamp": "2026-01-14T11:13:52.588031+00:00Z",
        "changes": [
            {
                "team": null,
                "service": null,
                "field": "housefire_reference_latest_block_height",
                "full_path": "housefire_reference_latest_block_height",
                "type": "modified",
                "old_value": "4051633",
                "new_value": "4051843"
            }
        ]
    },
    {
        "timestamp": "2026-01-14T11:28:25.751978+00:00Z",
        "changes": [
            {
                "team": null,
                "service": null,
                "field": "housefire_reference_latest_block_height",
                "full_path": "housefire_reference_latest_block_height",
                "type": "modified",
                "old_value": "4051633",
                "new_value": "4052046"
            }
        ]
    }
]