[
    {
        "timestamp": "2026-02-06T09:10:41.122261+00:00Z",
        "changes": [
            {
                "team": null,
                "service": null,
                "field": "housefire_reference_latest_block_height",
                "full_path": "housefire_reference_latest_block_height",
                "type": "modified",
                "old_value": "4283108",
                "new_value": "4283479"
            }
        ]
    },
    {
        "timestamp": "2026-02-06T10:03:50.773535+00:00Z",
        "changes": [
            {
                "team": null,
                "service": null,
                "field": "housefire_reference_latest_block_height",
                "full_path": "housefire_reference_latest_block_height",
                "type": "modified",
                "old_value": "4283479",
                "new_value": "4283915"
            }
        ]
    },
    {
        "timestamp": "2026-02-06T10:08:35.277464+00:00Z",
        "changes": [
            {
                "team": null,
                "service": null,
                "field": "housefire_reference_latest_block_height",
                "full_path": "housefire_reference_latest_block_height",
                "type": "modified",
                "old_value": "4283479",
                "new_value": "4283915"
            }
        ]
    },
    {
        "timestamp": "2026-02-06T11:05:02.438883+00:00Z",
        "changes": [
            {
                "team": null,
                "service": null,
                "field": "housefire_reference_latest_block_height",
                "full_path": "housefire_reference_latest_block_height",
                "type": "modified",
                "old_value": "4283915",
                "new_value": "4284312"
            }
        ]
    },
    {
        "timestamp": "2026-02-06T11:08:24.140244+00:00Z",
        "changes": [
            {
                "team": null,
                "service": null,
                "field": "housefire_reference_latest_block_height",
                "full_path": "housefire_reference_latest_block_height",
                "type": "modified",
                "old_value": "4283915",
                "new_value": "4284312"
            }
        ]
    },
    {
        "timestamp": "2026-02-06T11:52:20.369139+00:00Z",
        "changes": [
            {
                "team": null,
                "service": null,
                "field": "housefire_reference_latest_block_height",
                "full_path": "housefire_reference_latest_block_height",
                "type": "modified",
                "old_value": "4284312",
                "new_value": "4284702"
            }
        ]
    },
    {
        "timestamp": "2026-02-06T11:56:48.830297+00:00Z",
        "changes": [
            {
                "team": null,
                "service": null,
                "field": "housefire_reference_latest_block_height",
                "full_path": "housefire_reference_latest_block_height",
                "type": "modified",
                "old_value": "4284312",
                "new_value": "4284702"
            }
        ]
    },
    {
        "timestamp": "2026-02-06T12:36:51.359736+00:00Z",
        "changes": [
            {
                "team": null,
                "service": null,
                "field": "housefire_reference_latest_block_height",
                "full_path": "housefire_reference_latest_block_height",
                "type": "modified",
                "old_value": "4284702",
                "new_value": "4284891"
            }
        ]
    },
    {
        "timestamp": "2026-02-06T13:19:55.057225+00:00Z",
        "changes": [
            {
                "team": null,
                "service": null,
                "field": "housefire_reference_latest_block_height",
                "full_path": "housefire_reference_latest_block_height",
                "type": "modified",
                "old_value": "4284702",
                "new_value": "4285335"
            }
        ]
    },
    {
        "timestamp": "2026-02-06T13:55:17.074842+00:00Z",
        "changes": [
            {
                "team": null,
                "service": null,
                "field": "housefire_reference_latest_block_height",
                "full_path": "housefire_reference_latest_block_height",
                "type": "modified",
                "old_value": "4284891",
                "new_value": "4285335"
            }
        ]
    },
    {
        "timestamp": "2026-02-06T14:23:44.670287+00:00Z",
        "changes": [
            {
                "team": null,
                "service": null,
                "field": "housefire_reference_latest_block_height",
                "full_path": "housefire_reference_latest_block_height",
                "type": "modified",
                "old_value": "4285335",
                "new_value": "4285797"
            }
        ]
    },
    {
        "timestamp": "2026-02-06T14:35:21.451035+00:00Z",
        "changes": [
            {
                "team": null,
                "service": null,
                "field": "housefire_reference_latest_block_height",
                "full_path": "housefire_reference_latest_block_height",
                "type": "modified",
                "old_value": "4285335",
                "new_value": "4285797"
            }
        ]
    },
    {
        "timestamp": "2026-02-06T15:31:08.947059+00:00Z",
        "changes": [
            {
                "team": null,
                "service": null,
                "field": "housefire_reference_latest_block_height",
                "full_path": "housefire_reference_latest_block_height",
                "type": "modified",
                "old_value": "4285797",
                "new_value": "4286228"
            }
        ]
    },
    {
        "timestamp": "2026-02-06T16:33:23.217192+00:00Z",
        "changes": [
            {
                "team": null,
                "service": null,
                "field": "housefire_reference_latest_block_height",
                "full_path": "housefire_reference_latest_block_height",
                "type": "modified",
                "old_value": "4286228",
                "new_value": "4286625"
            }
        ]
    },
    {
        "timestamp": "2026-02-06T16:06:51.557083+00:00Z",
        "changes": [
            {
                "team": null,
                "service": null,
                "field": "housefire_reference_latest_block_height",
                "full_path": "housefire_reference_latest_block_height",
                "type": "modified",
                "old_value": "4285797",
                "new_value": "4286228"
            }
        ]
    },
    {
        "timestamp": "2026-02-06T17:34:22.707130+00:00Z",
        "changes": [
            {
                "team": null,
                "service": null,
                "field": "housefire_reference_latest_block_height",
                "full_path": "housefire_reference_latest_block_height",
                "type": "modified",
                "old_value": "4286625",
                "new_value": "4287099"
            }
        ]
    },
    {
        "timestamp": "2026-02-06T17:22:39.897510+00:00Z",
        "changes": [
            {
                "team": null,
                "service": null,
                "field": "housefire_reference_latest_block_height",
                "full_path": "housefire_reference_latest_block_height",
                "type": "modified",
                "old_value": "4286228",
                "new_value": "4287099"
            }
        ]
    },
    {
        "timestamp": "2026-02-06T18:34:47.774612+00:00Z",
        "changes": [
            {
                "team": null,
                "service": null,
                "field": "housefire_reference_latest_block_height",
                "full_path": "housefire_reference_latest_block_height",
                "type": "modified",
                "old_value": "4287099",
                "new_value": "4287482"
            }
        ]
    },
    {
        "timestamp": "2026-02-06T19:31:22.937368+00:00Z",
        "changes": [
            {
                "team": null,
                "service": null,
                "field": "housefire_reference_latest_block_height",
                "full_path": "housefire_reference_latest_block_height",
                "type": "modified",
                "old_value": "4287482",
                "new_value": "4287958"
            }
        ]
    },
    {
        "timestamp": "2026-02-06T19:23:01.791864+00:00Z",
        "changes": [
            {
                "team": null,
                "service": null,
                "field": "housefire_reference_latest_block_height",
                "full_path": "housefire_reference_latest_block_height",
                "type": "modified",
                "old_value": "4287099",
                "new_value": "4287958"
            }
        ]
    },
    {
        "timestamp": "2026-02-06T20:23:03.714482+00:00Z",
        "changes": [
            {
                "team": null,
                "service": null,
                "field": "housefire_reference_latest_block_height",
                "full_path": "housefire_reference_latest_block_height",
                "type": "modified",
                "old_value": "4287958",
                "new_value": "4288252"
            }
        ]
    },
    {
        "timestamp": "2026-02-06T20:47:10.385462+00:00Z",
        "changes": [
            {
                "team": null,
                "service": null,
                "field": "housefire_reference_latest_block_height",
                "full_path": "housefire_reference_latest_block_height",
                "type": "modified",
                "old_value": "4287958",
                "new_value": "4288495"
            }
        ]
    },
    {
        "timestamp": "2026-02-06T20:56:04.649357+00:00Z",
        "changes": [
            {
                "team": null,
                "service": null,
                "field": "housefire_reference_latest_block_height",
                "full_path": "housefire_reference_latest_block_height",
                "type": "modified",
                "old_value": "4288252",
                "new_value": "4288495"
            }
        ]
    },
    {
        "timestamp": "2026-02-06T21:24:24.002213+00:00Z",
        "changes": [
            {
                "team": null,
                "service": null,
                "field": "housefire_reference_latest_block_height",
                "full_path": "housefire_reference_latest_block_height",
                "type": "modified",
                "old_value": "4288495",
                "new_value": "4288710"
            }
        ]
    },
    {
        "timestamp": "2026-02-06T21:38:53.756804+00:00Z",
        "changes": [
            {
                "team": null,
                "service": null,
                "field": "housefire_reference_latest_block_height",
                "full_path": "housefire_reference_latest_block_height",
                "type": "modified",
                "old_value": "4288495",
                "new_value": "4288710"
            }
        ]
    },
    {
        "timestamp": "2026-02-06T21:50:47.998047+00:00Z",
        "changes": [
            {
                "team": null,
                "service": null,
                "field": "housefire_reference_latest_block_height",
                "full_path": "housefire_reference_latest_block_height",
                "type": "modified",
                "old_value": "4288710",
                "new_value": "4288981"
            }
        ]
    },
    {
        "timestamp": "2026-02-06T22:34:19.198366+00:00Z",
        "changes": [
            {
                "team": null,
                "service": null,
                "field": "housefire_reference_latest_block_height",
                "full_path": "housefire_reference_latest_block_height",
                "type": "modified",
                "old_value": "4288710",
                "new_value": "4289274"
            }
        ]
    }
]