[
    {
        "timestamp": "2026-01-02T19:33:31.321361+00:00Z",
        "changes": [
            {
                "team": "TuDudes",
                "service": "masp",
                "field": "sync_state",
                "full_path": "namada.operator.TuDudes.service.masp.sync_state",
                "type": "modified",
                "old_value": "sync_nok",
                "new_value": "sync_lag"
            }
        ]
    },
    {
        "timestamp": "2026-01-02T19:41:39.451861+00:00Z",
        "changes": [
            {
                "team": "TuDudes",
                "service": "masp",
                "field": "latest_block_height",
                "full_path": "namada.operator.TuDudes.service.masp.latest_block_height",
                "type": "modified",
                "old_value": "4895474",
                "new_value": "4896231"
            },
            {
                "team": "TuDudes",
                "service": "masp",
                "field": "sync_state",
                "full_path": "namada.operator.TuDudes.service.masp.sync_state",
                "type": "modified",
                "old_value": "sync_nok",
                "new_value": "sync_lag"
            }
        ]
    },
    {
        "timestamp": "2026-01-02T20:13:28.140332+00:00Z",
        "changes": [
            {
                "team": "TuDudes",
                "service": "masp",
                "field": "sync_state",
                "full_path": "namada.operator.TuDudes.service.masp.sync_state",
                "type": "modified",
                "old_value": "sync_lag",
                "new_value": "sync_nok"
            }
        ]
    },
    {
        "timestamp": "2026-01-02T20:30:44.374072+00:00Z",
        "changes": [
            {
                "team": "TuDudes",
                "service": "masp",
                "field": "latest_block_height",
                "full_path": "namada.operator.TuDudes.service.masp.latest_block_height",
                "type": "modified",
                "old_value": "4896231",
                "new_value": "4896694"
            },
            {
                "team": "TuDudes",
                "service": "masp",
                "field": "sync_state",
                "full_path": "namada.operator.TuDudes.service.masp.sync_state",
                "type": "modified",
                "old_value": "sync_lag",
                "new_value": "sync_nok"
            }
        ]
    }
]